pysilico/__init__.py
pysilico/__version__.py
pysilico/calibration/__init__.py
pysilico/calibration/abstract_calibration_manager.py
pysilico/calibration/calibration_manager.py
pysilico/calibration/in_memory_calibration_manager.py
pysilico/client/__init__.py
pysilico/client/abstract_camera_client.py
pysilico/client/camera_client.py
pysilico/client/cblue_client.py
pysilico/client/client_map.py
pysilico/client/ocam2k_client.py
pysilico/client/simulated_camera_client.py
pysilico/gui/__init__.py
pysilico/gui/cameraWidget.ui
pysilico/gui/camera_control_gui.py
pysilico/gui/camera_control_gui.ui
pysilico/gui/camera_control_gui_ui.py
pysilico/gui/pysilico_gui.py
pysilico/gui/image_show_widget/__init__.py
pysilico/gui/image_show_widget/image_show_basic_widget.py
pysilico/gui/image_show_widget/image_show_basic_widget_ui.py
pysilico/types/__init__.py
pysilico/types/camera_frame.py
pysilico/types/camera_status.py
pysilico/utils/__init__.py
pysilico/utils/constants.py
pysilico/utils/timeout.py
pysilico-0.22.0.dist-info/licenses/LICENSE
pysilico-0.22.0.dist-info/METADATA
pysilico-0.22.0.dist-info/WHEEL
pysilico-0.22.0.dist-info/entry_points.txt
pysilico-0.22.0.dist-info/top_level.txt
pysilico-0.22.0.dist-info/RECORD
