Metadata-Version: 2.4
Name: pysilico
Version: 0.22.0
Summary: Allied Vision AVT-Prosilica camera controller with PLICO
Home-page: https://github.com/lbusoni/pysilico
Author: Lorenzo Busoni
Author-email: lorenzo.busoni@inaf.it
License: MIT
Keywords: plico, prosilica, avt, camera, laboratory, instrumentation control
Classifier: Development Status :: 4 - Beta
Classifier: Operating System :: POSIX :: Linux
Classifier: Programming Language :: Python :: 3
License-File: LICENSE
Requires-Dist: plico>=0.29
Requires-Dist: numpy
Requires-Dist: six
Requires-Dist: astropy
Requires-Dist: pyqtgraph
Requires-Dist: PyQt5
Dynamic: author
Dynamic: author-email
Dynamic: classifier
Dynamic: description
Dynamic: description-content-type
Dynamic: home-page
Dynamic: keywords
Dynamic: license
Dynamic: license-file
Dynamic: requires-dist
Dynamic: summary
